xls_cli/__init__.py
xls_cli/ansi.py
xls_cli/cli.py
xls_cli/frame.py
xls_cli/grid.py
xls_cli/runner.py
xls_cli-1.0.2.dist-info/LICENSE
xls_cli-1.0.2.dist-info/METADATA
xls_cli-1.0.2.dist-info/WHEEL
xls_cli-1.0.2.dist-info/entry_points.txt
xls_cli-1.0.2.dist-info/top_level.txt
xls_cli-1.0.2.dist-info/RECORD
