Metadata-Version: 2.1
Name: xls-cli
Version: 1.0.2
Summary: It is a simple python package to explore xls files in the terminal
Home-page: https://github.com/joelibaceta/xls-cli
Author: Joel Ibaceta
Author-email: mail@joelibaceta.com
License: MIT
Project-URL: Source, https://github.com/joelibaceta/xls-cli
Project-URL: Tracker, https://github.com/joelibaceta/xls-cli/issues
Keywords: xls terminal excel spreadsheet
Platform: UNKNOWN
Classifier: Programming Language :: Python :: 3
Classifier: Intended Audience :: Developers
Classifier: License :: OSI Approved :: MIT License
Classifier: Operating System :: OS Independent
Requires-Dist: xlrd
Requires-Dist: getkey
